odoo/addons/sale_automatic_workflow_job/README.rst
odoo/addons/sale_automatic_workflow_job/__init__.py
odoo/addons/sale_automatic_workflow_job/__manifest__.py
odoo/addons/sale_automatic_workflow_job/data/queue_job_data.xml
odoo/addons/sale_automatic_workflow_job/i18n/sale_automatic_workflow_job.pot
odoo/addons/sale_automatic_workflow_job/models/__init__.py
odoo/addons/sale_automatic_workflow_job/models/automatic_workflow_job.py
odoo/addons/sale_automatic_workflow_job/models/queue_job.py
odoo/addons/sale_automatic_workflow_job/readme/CONTRIBUTORS.rst
odoo/addons/sale_automatic_workflow_job/readme/DESCRIPTION.rst
odoo/addons/sale_automatic_workflow_job/static/description/icon.png
odoo/addons/sale_automatic_workflow_job/static/description/index.html
odoo/addons/sale_automatic_workflow_job/tests/__init__.py
odoo/addons/sale_automatic_workflow_job/tests/test_auto_workflow_job.py
odoo13_addon_sale_automatic_workflow_job-13.0.1.0.1.dev3.dist-info/METADATA
odoo13_addon_sale_automatic_workflow_job-13.0.1.0.1.dev3.dist-info/WHEEL
odoo13_addon_sale_automatic_workflow_job-13.0.1.0.1.dev3.dist-info/top_level.txt
odoo13_addon_sale_automatic_workflow_job-13.0.1.0.1.dev3.dist-info/RECORD
